[
  {
    "year": 2026,
    "last_modified": "2025-11-22 12:55:00"
  },
  {
    "year": 2025,
    "last_modified": "2024-11-30 20:41:00"
  },
  {
    "year": 2024,
    "last_modified": "2023-11-08 16:31:00"
  },
  {
    "year": 2023,
    "last_modified": "2022-12-10 10:02:00"
  },
  {
    "year": 2022,
    "last_modified": "2021-11-02 16:02:00"
  },
  {
    "year": 2021,
    "last_modified": "2020-12-09 08:52:00"
  },
  {
    "year": 2020,
    "last_modified": "2019-11-22 10:11:00"
  },
  {
    "year": 2019,
    "last_modified": "2019-04-07 18:09:00"
  },
  {
    "year": 2018,
    "last_modified": "2017-12-29 15:44:00"
  },
  {
    "year": 2017,
    "last_modified": "2017-03-20 23:28:00"
  },
  {
    "year": 2016,
    "last_modified": "2016-06-28 22:43:00"
  }
]
